types_aiobotocore_simspaceweaver/__init__.py
types_aiobotocore_simspaceweaver/__init__.pyi
types_aiobotocore_simspaceweaver/__main__.py
types_aiobotocore_simspaceweaver/client.py
types_aiobotocore_simspaceweaver/client.pyi
types_aiobotocore_simspaceweaver/literals.py
types_aiobotocore_simspaceweaver/literals.pyi
types_aiobotocore_simspaceweaver/py.typed
types_aiobotocore_simspaceweaver/type_defs.py
types_aiobotocore_simspaceweaver/type_defs.pyi
types_aiobotocore_simspaceweaver/version.py
types_aiobotocore_simspaceweaver-3.1.1.dist-info/licenses/LICENSE
types_aiobotocore_simspaceweaver-3.1.1.dist-info/METADATA
types_aiobotocore_simspaceweaver-3.1.1.dist-info/WHEEL
types_aiobotocore_simspaceweaver-3.1.1.dist-info/top_level.txt
types_aiobotocore_simspaceweaver-3.1.1.dist-info/RECORD
