Metadata-Version: 2.4
Name: types-aiobotocore-simspaceweaver
Version: 3.1.1
Summary: Type annotations for aiobotocore SimSpaceWeaver 3.1.1 service generated with mypy-boto3-builder 8.12.0
Author-email: Vlad Emelianov <vlad.emelianov.nz@gmail.com>
License-Expression: MIT
Project-URL: Homepage, https://github.com/youtype/mypy_boto3_builder
Project-URL: Documentation, https://youtype.github.io/types_aiobotocore_docs/types_aiobotocore_simspaceweaver/
Project-URL: Source, https://github.com/youtype/mypy_boto3_builder
Project-URL: Tracker, https://github.com/youtype/mypy_boto3_builder/issues
Keywords: aiobotocore,simspaceweaver,aiobotocore-stubs,type-annotations,mypy,typeshed,autocomplete
Platform: any
Classifier: Development Status :: 5 - Production/Stable
Classifier: Intended Audience :: Developers
Classifier: Environment :: Console
Classifier: Natural Language :: English
Classifier: Operating System :: OS Independent
Classifier: Programming Language :: Python :: 3
Classifier: Programming Language :: Python :: 3.9
Classifier: Programming Language :: Python :: 3.10
Classifier: Programming Language :: Python :: 3.11
Classifier: Programming Language :: Python :: 3.12
Classifier: Programming Language :: Python :: 3.13
Classifier: Programming Language :: Python :: 3.14
Classifier: Programming Language :: Python :: 3 :: Only
Classifier: Programming Language :: Python :: Implementation :: CPython
Classifier: Typing :: Stubs Only
Requires-Python: >=3.9
License-File: LICENSE
Requires-Dist: typing-extensions; python_version < "3.12"
Dynamic: license-file
